docs/Makefile
docs/authors.md
docs/changelog.md
docs/conf.py
docs/contributing.md
docs/index.md
docs/license.md
docs/readme.md
docs/requirements.txt
docs/_static/.gitignore
docs/_static/custom.css
reptrix/__init__.py
reptrix/alpha.py
reptrix/lidar.py
reptrix/rankme.py
reptrix/test_lidar.py
reptrix/utils.py
reptrix-0.1.0.dist-info/LICENSE.txt
reptrix-0.1.0.dist-info/METADATA
reptrix-0.1.0.dist-info/WHEEL
reptrix-0.1.0.dist-info/top_level.txt
reptrix-0.1.0.dist-info/RECORD
