Metadata-Version: 2.2
Name: reptrix
Version: 0.1.0
Summary: Library that provides metrics to assess representation quality
Home-page: https://github.com/BARL-SSL/reptrix/
Author: Arnab Mondal, Arna Ghosh, Danielle Benesch
Author-email: arnab.mondal@mila.quebec, ghosharn@mila.quebec, daniellerbenesch@gmail.com
License: MIT
Project-URL: Tracker, https://github.com/BARL-SSL/reptrix/issues
Project-URL: Source, https://github.com/BARL-SSL/reptrix/
Platform: any
Classifier: Programming Language :: Python :: 3
Classifier: License :: OSI Approved :: MIT License
Classifier: Operating System :: OS Independent
Requires-Python: >=3.8
License-File: LICENSE.txt
Requires-Dist: importlib-metadata
Requires-Dist: torch
Requires-Dist: numpy
Requires-Dist: scikit-learn
Requires-Dist: matplotlib
Requires-Dist: torchvision
Provides-Extra: testing
Requires-Dist: setuptools; extra == "testing"
Requires-Dist: pytest; extra == "testing"
Requires-Dist: pytest-cov; extra == "testing"
